[
  {
    "userUid": "275714057",
    "taskType": "local",
    "timestamp": "2026-07-04T02:24:21.873Z",
    "clientType": "chrome-extension",
    "totalParsed": 24,
    "submitted": 24,
    "failed": 0,
    "whitelistSkipped": 0,
    "durationSeconds": 349,
    "received_at": "2026-07-04T02:24:41.164020Z"
  },
  {
    "userUid": "275714057",
    "taskType": "local",
    "timestamp": "2026-07-04T02:31:42.447Z",
    "clientType": "chrome-extension",
    "totalParsed": 24,
    "submitted": 23,
    "failed": 1,
    "whitelistSkipped": 0,
    "durationSeconds": 369,
    "received_at": "2026-07-04T02:31:40.622114Z"
  },
  {
    "userUid": "275714057",
    "taskType": "local",
    "timestamp": "2026-07-04T02:41:43.286Z",
    "clientType": "chrome-extension",
    "totalParsed": 24,
    "submitted": 24,
    "failed": 0,
    "whitelistSkipped": 0,
    "durationSeconds": 348,
    "received_at": "2026-07-04T02:41:41.315935Z"
  },
  {
    "userUid": "274460833",
    "taskType": "temp",
    "totalParsed": 160,
    "submitted": 153,
    "failed": 0,
    "whitelistSkipped": 7,
    "durationSeconds": 2164,
    "timestamp": "2026-07-04T10:43:08.517680",
    "clientType": "android-apk",
    "received_at": "2026-07-04T02:43:09.619353Z"
  },
  {
    "userUid": "275714057",
    "taskType": "local",
    "timestamp": "2026-07-04T02:48:08.547Z",
    "clientType": "chrome-extension",
    "totalParsed": 24,
    "submitted": 24,
    "failed": 0,
    "whitelistSkipped": 0,
    "durationSeconds": 346,
    "received_at": "2026-07-04T02:48:06.718062Z"
  },
  {
    "userUid": "262887342",
    "taskType": "temp",
    "totalParsed": 191,
    "submitted": 184,
    "failed": 0,
    "whitelistSkipped": 7,
    "durationSeconds": 1797,
    "timestamp": "2026-07-04T10:50:24.765746",
    "clientType": "android-apk",
    "received_at": "2026-07-04T02:50:27.584543Z"
  },
  {
    "userUid": "275714057",
    "taskType": "local",
    "timestamp": "2026-07-04T02:56:10.031Z",
    "clientType": "chrome-extension",
    "totalParsed": 24,
    "submitted": 24,
    "failed": 0,
    "whitelistSkipped": 0,
    "durationSeconds": 347,
    "received_at": "2026-07-04T02:56:08.073963Z"
  },
  {
    "userUid": "275714057",
    "taskType": "local",
    "timestamp": "2026-07-04T03:02:35.472Z",
    "clientType": "chrome-extension",
    "totalParsed": 24,
    "submitted": 24,
    "failed": 0,
    "whitelistSkipped": 0,
    "durationSeconds": 368,
    "received_at": "2026-07-04T03:02:33.515235Z"
  },
  {
    "userUid": "282772777",
    "taskType": "temp",
    "totalParsed": 160,
    "submitted": 153,
    "failed": 0,
    "whitelistSkipped": 7,
    "durationSeconds": 1947,
    "timestamp": "2026-07-04T11:04:18.313910",
    "clientType": "android-apk",
    "received_at": "2026-07-04T03:04:19.465061Z"
  }
]
