{
  "month": "2026-07",
  "days": {
    "2026-07-01": {
      "date": "2026-07-01",
      "recordsPath": "archive/reports/2026/07/2026-07-01.json",
      "reportCount": 7,
      "activeUsers": 7,
      "totalParsed": 6870,
      "submitted": 2671,
      "failed": 4106,
      "whitelistSkipped": 93,
      "durationSeconds": 35036,
      "taskTypes": {
        "daily": 0,
        "temp": 3,
        "local": 4,
        "unknown": 0
      },
      "lastSeenAt": "2026-07-01T21:40:59.736809Z",
      "updatedAt": "2026-07-01T13:56:24.150005Z"
    },
    "2026-07-02": {
      "date": "2026-07-02",
      "recordsPath": "archive/reports/2026/07/2026-07-02.json",
      "reportCount": 286,
      "activeUsers": 124,
      "totalParsed": 369336,
      "submitted": 259229,
      "failed": 47804,
      "whitelistSkipped": 2474,
      "durationSeconds": 2145082,
      "taskTypes": {
        "daily": 7,
        "temp": 123,
        "local": 156,
        "unknown": 0
      },
      "lastSeenAt": "2026-07-02T23:40:10.318276Z",
      "updatedAt": "2026-07-02T15:40:12.128680Z"
    }
  },
  "updatedAt": "2026-07-02T15:40:12.128690Z"
}
